hommmer/__init__.py
hommmer/main.py
hommmer/charts/__init__.py
hommmer/charts/accuracy.py
hommmer/charts/heatmap.py
hommmer/charts/lineplot.py
hommmer/charts/pairplot.py
hommmer/charts/response.py
hommmer/charts/y_corr.py
hommmer/cleaners/__init__.py
hommmer/cleaners/add_X_labels.py
hommmer/cleaners/cat_to_dummies.py
hommmer/cleaners/categorize_campaigns.py
hommmer/cleaners/clean_numeric.py
hommmer/cleaners/convert_date.py
hommmer/cleaners/count_dup_cols.py
hommmer/cleaners/count_na.py
hommmer/cleaners/count_na_cols.py
hommmer/cleaners/date_range_dummies.py
hommmer/cleaners/days_in_month.py
hommmer/cleaners/del_X_labels.py
hommmer/cleaners/describe_data.py
hommmer/cleaners/drop_cols.py
hommmer/cleaners/drop_n_rows.py
hommmer/cleaners/end_of_month.py
hommmer/cleaners/get_all_X_labels.py
hommmer/cleaners/get_cols_containing.py
hommmer/cleaners/group_monthly.py
hommmer/cleaners/group_weekly.py
hommmer/cleaners/guess_date_column.py
hommmer/cleaners/guess_media_columns.py
hommmer/cleaners/guess_y_column.py
hommmer/cleaners/holiday_dummies.py
hommmer/cleaners/interpolate_dates.py
hommmer/cleaners/interpolate_monthly.py
hommmer/cleaners/interpolate_weekly.py
hommmer/cleaners/make_column_index.py
hommmer/cleaners/make_date_index.py
hommmer/cleaners/merge_data.py
hommmer/cleaners/modify_labels.py
hommmer/cleaners/payday_dummies.py
hommmer/cleaners/remove_outliers.py
hommmer/cleaners/rename_column.py
hommmer/cleaners/standard_scaler.py
hommmer/cleaners/start_of_month.py
hommmer/cleaners/str_to_dummy.py
hommmer/cleaners/train_test_split.py
hommmer/cleaners/transpose_data.py
hommmer/cleaners/unstack_data.py
hommmer/cleaners/week_commencing.py
hommmer/connectors/__init__.py
hommmer/connectors/colab_helpers.py
hommmer/connectors/covid_mobility.py
hommmer/connectors/nasa_weather.py
hommmer/connectors/search_trends.py
hommmer/data/__init__.py
hommmer/datasets/__init__.py
hommmer/datasets/add_noise.py
hommmer/datasets/load_duff.py
hommmer/datasets/make_data.py
hommmer-0.0.0.4.dist-info/LICENSE
hommmer-0.0.0.4.dist-info/METADATA
hommmer-0.0.0.4.dist-info/WHEEL
hommmer-0.0.0.4.dist-info/top_level.txt
hommmer-0.0.0.4.dist-info/RECORD
