Metadata-Version: 2.1
Name: hommmer
Version: 0.0.0.4
Summary: A simple Marketing Mix Modeling library in Python
Home-page: https://github.com/hammer-mt/hommmer
Author: mike taylor
Author-email: mike@saxifrage.xyz
License: MIT
Platform: UNKNOWN
Requires-Dist: numpy
Requires-Dist: pandas
Requires-Dist: matplotlib
Requires-Dist: statsmodels
Requires-Dist: typing
Requires-Dist: sklearn
Requires-Dist: seaborn
Requires-Dist: prophet
